{
  "act_id": "the_metro_railways_construction_of_works_act_1978__1737",
  "section_number": "29",
  "section_id": "24156",
  "title": "Section 29",
  "content": "Every metro railway administration shall afford to every commissioner all reasonable facilities for performing the duties or exercising the powers imposed or conferred upon him by or under this Act.",
  "footnote": "",
  "metadata": {
    "source": "IndiaCode",
    "act_url": "https://www.indiacode.nic.in/handle/123456789/1737?view_type=browse",
    "fetched_at": "2026-03-02T11:03:11.623Z"
  }
}