{
  "act_id": "the_emigration_act_1983__1779",
  "section_number": "14",
  "section_id": "4187",
  "title": "Section 14",
  "content": "(1) The registering authority may cancel any certificate on any one or more of the following grounds and on no other ground namely:-- (a) that having regard to the manner in which the holder of the certificate has carried on his business or any deterioration in his financial position, the facilities at his disposal for recruitment, the holder of the certificate is not a fit person to continue to hold the certificate; (b) that the holder of the certificate has recruited emigrants for purposes prejudicial to the interests of India or for purposes contrary to public policy; (c) that the holder of the certificate has, subsequent to the issue of the certificate, been convicted in India for any offence involving moral turpitude; (d) that the holder of the certificate has, subsequent to the issue of the certificate, been convicted by a court in India for any offence under this Act, the Emigration Act, 1922 (7 of 1922), or any other law relating to passports, foreign exchange, drugs, narcotics or smuggling and sentenced in respect thereof to imprisonment for not less than six months; (e) that the certificate has been issued or renewed on misrepresentation or suppression of any material fact; (f) that the holder of the certificate has violated any of the terms and conditions of the certificate; (g) that in the opinion of the Central Government it is necessary in the interests of friendly relations of India with any foreign country or in the interests of the general public to cancel the certificate. (2) Where the registering authority, for reasons to be recorded in writing, is satisfied that pending the consideration of the question of cancelling any certificate on any of the grounds mentioned in sub-section (1) it is necessary so to do, the registering authority may, by order in writing, suspend the operation of the certificate for such period not exceeding thirty days as may be specified in the order and require the holder of the certificate to show cause, within fifteen days from the date of receipt of such order, as to why the suspension of the certificate should not be extended till the determination of the question as to whether the registration should be cancelled. (3) A court convicting a holder of a certificate for an offence under this Act may also cancel the certificate: Provided that if the conviction is set aside in appeal or otherwise, the cancellation under sub-section (3) shall become void. (4) An order of cancellation of a certificate may be made under sub-section (3) by an appellate court or by a court exercising its powers of revision. (5) Before passing an order cancelling or suspending a certificate the registering authority or the court, as the case may be, shall consider the question as to the provisions and arrangements which should be made for safeguarding the interests of emigrants and other persons with whom the holder of the certificate had any transactions in the course of his business as recruiting agent and may make such orders (including orders permitting the holder of the certificate to continue to carry on his business with respect to all or any such emigrants and other persons) as it may consider necessary in this behalf. (6) Where a certificate issued to any person has been cancelled under this section, such person shall not be eligible to make any application for another certificate under this Chapter until the expiry of a period of two years from the date of such cancellation.",
  "footnote": "",
  "metadata": {
    "source": "IndiaCode",
    "act_url": "https://www.indiacode.nic.in/handle/123456789/1779?view_type=browse",
    "fetched_at": "2026-03-02T11:10:38.306Z"
  }
}