{
  "act_id": "the_administrators-general_act_1963__1567",
  "section_number": "50",
  "section_id": "29154",
  "title": "Section 50",
  "content": "Whoever, during any examination authorised by this Act, makes upon oath a statement which is false and which he either knows or believes to be false or does not believe to be true, shall be deemed to have intentionally given false evidence in a stage of a judicial proceeding.",
  "footnote": "",
  "metadata": {
    "source": "IndiaCode",
    "act_url": "https://www.indiacode.nic.in/handle/123456789/1567?view_type=browse",
    "fetched_at": "2026-03-02T10:40:51.679Z"
  }
}