{
  "sub_id": "notifications_20-10-2017_nomination_of_member_ncm_efd9edda20c1_",
  "parent_act_id": "the_national_commission_for_minorities_act_1992__1927",
  "title": "Nomination of Member, NCM",
  "type": "notification",
  "category_label": "Notifications",
  "source": "IndiaCode",
  "source_url": "https://www.indiacode.nic.in/ViewFileUploaded?path=AC_CEN_41_69_00001_199219_1517807322944/notificationindividualfile/&file=2976.pdf",
  "detection_method": "modal-table-scan",
  "document_date": "20-10-2017",
  "description": "Nomination of Member, NCM",
  "hindi_description": null,
  "file_title": "2976.pdf",
  "duplicate_count": 0,
  "alternate_source_urls": [],
  "alternate_file_titles": [],
  "alternate_descriptions": [],
  "document_format": "pdf",
  "extraction": {
    "content_type": "application/pdf",
    "final_url": "https://upload.indiacode.nic.in/showfile?actid=AC_CEN_41_69_00001_199219_1517807322944&type=notification&filename=2976.pdf",
    "num_pages": 1,
    "parser": "pdf-parse",
    "status": "parsed",
    "error_message": null,
    "error_code": null,
    "error_status": null
  },
  "text": "• ~ ~o \"ito ~o-33004/99 REGD. NO. D. L.-33004/99 ([he (5a'Lette of .3ndia ~ EXTRAORDINARY mlf 1l-<90S 3-\"3tf-<90S (ii) PART II-Section 3-Sub-section (ii) ~it~ PUBLISHED BY AUTHORITY -«. 2976] No. 2976] ~~,~,~21,2017/~ 29,1939 NEW DELHI, SATURDAY, OCTOBER 21, 2017/ASVINA 29,1939 31(\"q 'fiM<ti q;nf ~ 0I~<i\"''11 \"<li ~. 20~. 2017 <fiT.lIIT.3396(0I).-~ \"fIm ~ 31('(H-iM4i ~ (~) ~. 1995 (1995 \"4iT 44) ~ ~ ~ ~ 31('q'l-iM4i ~ ~. 1992 (1992 \"4iT 19) ~ trRT31T 3(2). 4(1) Clm 4(4) ct X1T~ ~ trRT 3 ~ \\')q-trRT 1 &RT ~ ~ \"4iT ~ ~ ~ C!dC\\E;I't1 ~ ~ ~ xn:r q;l ~ lJ5UT ~ ~ ~ ~ ~ crm ~ ~ ct ~ ~ ~ ct ~ ct ~ B ~ ~ tl [\"fl. 1-19/2015-~ (l:lli)] ~. \"ttT. ~. ~ mwr MINISTRY OF MINORITY AFFAIRS NOTIFICATION New Delhi. the 20th October, 2017 S.O. 3396(E).-In exercise of the powers conferred by sub-section (I) of Section 3 read with Sections 3(2). 4(1) and 4(4) of the National Commission for Minorities Act, 1992 (19 of 1992) as amended vide the National Commission for Minorities (Amendment) Act. 1995 (44 of 1995), the Central Government hereby nominates Shri Manjit Singh Rai, as Member of the said Commission for a period of three years from the date of assumption of office by him. [No. 1-19/2015-NCM (Pt.») K. C. SAMRIA, Jt. Secy. 6332 CanOl7 Uploaded by Dte. of Printing at Government of India Press, Ring Road, Mayapuri, New Delhi-l 10064 and Published by the Controller of Publications, Delhi-I 10054. Digitally signed by RAKESH RAKESH SUKUL ~~;0171O.2418lS3' +05'30' -- 1 of 1 --",
  "fetched_at": "2026-04-11T16:39:23.781Z"
}
