{
  "act_id": "the_visva-bharati_act_1951__1652",
  "section_number": "39",
  "section_id": "41294",
  "title": "Section 39",
  "content": "(1) The University shall constitute, for the benefit of its officers [including the Upacharya (Vice-Chancellor)], 1[adhyapakas], and other servants, in such manner and subject to such conditions as may be prescribed by the Statutes, such pension, insurance and provident funds as it may deem fit. (2) Where any such pension, insurance or provident fund has been so constituted, the Central Government may declare that the provisions of the Provident Funds Act, 1925 (17 of 1925), shall apply to such fund as if it were a Government Provident Fund.",
  "footnote": "1. Subs. by Act 31 of 1984, s. 2, for \"teacher\" (w.e.f. 8-8-1984).",
  "metadata": {
    "source": "IndiaCode",
    "act_url": "https://www.indiacode.nic.in/handle/123456789/1652?view_type=browse",
    "fetched_at": "2026-03-02T10:01:44.020Z"
  }
}