{
  "sub_id": "regulations_15-10-2013_central_electricity_authority_technical_standards_for_connectivity_to_the_grid_amendment_regulations_2013_5984b08a9eff_",
  "parent_act_id": "the_electricity_act_2003__2058",
  "title": "Central Electricity Authority (Technical Standards for Connectivity to the Grid) Amendment Regulations, 2013",
  "type": "regulations",
  "category_label": "Regulations",
  "source": "IndiaCode",
  "source_url": "https://www.indiacode.nic.in/ViewFileUploaded?path=AC_CEN_19_22_00001_200336_1517807317930/regulationindividualfile/&file=File11.pdf",
  "detection_method": "modal-table-scan",
  "document_date": "15-10-2013",
  "description": "Central Electricity Authority (Technical Standards for Connectivity to the Grid) Amendment Regulations, 2013",
  "hindi_description": null,
  "file_title": "File11.pdf",
  "duplicate_count": 0,
  "alternate_source_urls": [],
  "alternate_file_titles": [],
  "alternate_descriptions": [],
  "document_format": "pdf",
  "extraction": {
    "content_type": "application/pdf",
    "final_url": "https://upload.indiacode.nic.in/showfile?actid=AC_CEN_19_22_00001_200336_1517807317930&type=regulation&filename=File11.pdf",
    "num_pages": 10,
    "parser": "pdf-parse",
    "status": "parsed",
    "error_message": null,
    "error_code": null,
    "error_status": null,
    "recovered_from_alternate_source": false,
    "attempted_urls": [
      "https://www.indiacode.nic.in/ViewFileUploaded?path=AC_CEN_19_22_00001_200336_1517807317930/regulationindividualfile/&file=File11.pdf",
      "https://upload.indiacode.nic.in/showfile?actid=AC_CEN_19_22_00001_200336_1517807317930&type=regulation&filename=File11.pdf",
      "https://www.indiacode.nic.in/showfile?actid=AC_CEN_19_22_00001_200336_1517807317930&type=regulation&filename=File11.pdf"
    ],
    "recovery_attempts": [
      {
        "url": "https://www.indiacode.nic.in/ViewFileUploaded?path=AC_CEN_19_22_00001_200336_1517807317930/regulationindividualfile/&file=File11.pdf",
        "finalUrl": "https://upload.indiacode.nic.in/showfile?actid=AC_CEN_19_22_00001_200336_1517807317930&type=regulation&filename=File11.pdf",
        "status": 200,
        "outcome": "parsed",
        "error": null
      }
    ]
  },
  "text": "~ tio ifo 'l@o- 33.004/99 ~- --.... REGb . NO. D. L. ;3 004/99 ~ I ti. 27lJ No. 2711 mmmvr EXTRAORDINARY 'qT1T Jll-(9Qs 4 PART III-Section 4 ~ \"« Yi:fiillii:1 PUBLISHED BY AUTHORITY ~ ~' q',1Hcm, ~ 15, 2013;~ 23, 1935 NEW DELHI, TUESDAY, OCTOBER 15, 2013/ASVINA 23~ 1935 fm.FI\"~ (~ ~ ~) . 3i°ft-t(i:!ill ~ ~' 15 ~/ 2013 _.· ~- 12/~/~ (~lt'h!i!Qil)/~I~-~ ~ ~ (fus '$ .f14icr1c1 ~ -~ aq-;;;ft$I ~l (m~). Rlfc?t4tt, 2012 c)i\" ~ 16 1ITTt, 2012 <.ITT ~ <~ ~r., c)j\" ~ i;rfff;mJ ~ 200s ~ ~ 3 ~ m2:f ~ ~ ~. 2003 (2003 cfiT 36) cfi'r 'URT 177 cfit\" ~ (2) '$ ~ ~ ~ ;JT'Q' ~; lR1= ~. ~ ~ 2003 cfi'r 'Um 7 Jm 'Um 13 cfiT m <~J '$ m~ i::rf3cf 177 cfi'I' ~ (2 > ~ ~ ~~ lfiT ~ ~ r1' ~ fctqn ~. ~ ~ ~ (Pls '$ .fi4).;ic-1 $ ~ ctcfi~~c81 ~) fc)f.:.l~cA . 2007 lfiT ~~ntloi W $ ~ fi-lMfi!IRslc1 Rlf..'14Ji ~ ~ :- ,. ~ ilm 3ftl \\1R3t: (1) ~ fc)~J.icHl lfiT ~ ~ ~ ~ ~ (f.trs c)j\" ~'Qi~- acfi~~&;'r ~) ('{1'~ftv.l;J l RI f.;'!i 4 Ji , 2013 ~ I <2J '4 Rlfc?t4Jl m it~ t;rclil~r., cfi'I' cl'Ttra cm-~ M 1 2. ~ ~ ~ ~ ~ <ti'-fl'11.-i cl;\" ~ (1\"1\"11cffl if!;iiqi) ftlfc!l-!.lcA, 2007 ;it (~ ~ - Qlfflra 3'cfn PlQ4cR ~ il'fllT f;) ~ Fclf:i.Q.it 2 'A- \"~-~\" ~ ~ 3!.-~ <t;r IDTI 'JR-~~~~ tp:cft' $ ~ ~ m- ~ ~ ~~i1 4414 0 1/2013 (J) -- 1 of 10 -- 2 THE GAZETTE OF INDIA : EXTRAORDINARY [PART Ill-SEC. 4] ,~ m c/i<\"'e.1~'11 JA~Ra, RQ~ <)) ~ ~ Q#IR-IQc ~ c); m2r ~ ~ V<ll q:~ ~ s,q1c::c1 ¥ c); ~ ~ ;i:rftjj mr - c.rrf.-m- (17) Qi\"~ ~ Qch,-fIB!flsla ~ ~ ~, M~:- . . ' . • f .' \"li~:iifac1 ~• ~ ~ 5qc):;~ m ~ ffclil41~ $ ~ q;f ~ ~ ~ ~ ~ f.tcra:q; cfi'r ~ 3i'R f.J:rs 'iji\" ~ ::t1~c14fa1cii ~~' fai?l1' -;;noT ~ 3frr ~ ~ ~ #cfc cni- ~ ~ 312:fcTT ~ rfi'l\"ar.rmtfr~cm-~c);fmr~l-'ll~1l'TQ\"af~~t° I (\"ETl l!is c1n c); trQ\"Wa fi!Mfi:li1sla ~ Jra: f~ ~ aTQ<JTT, 3f~:- (17<F) \"~' ~ ~ 7R ~ ~. ~~um ftt¥ cm q~ckh1 m 1,fr-41qc'ff cum~ at~ ~I (s.) ~ (19) c); m ~ ~M~Rslc1 ~ ~.-J1tim:- (19) \"~ m-<•i+< ttvr\" <~Jl'R> q'jf ~ ~ ~ ~ f<n ~ fcnJn ~ (~ ~ c'f:!IT fclWJ ~ <)) ~ c):; ~ c1cti.-1~cf?J ~l Rll\"cl4Ji, 2010 ~ ~ ~ 1 Cu) ~ (28} 'iji\" ~ti@ f.ilch-ffc;'.fl7iJa ~ 3fcf:~ fcnm aw.rrr. 3fmcJ:- (zsq;J \"~ &B;IT\" \"$\" ~ fctqa- ~ (~ ~ R~ ~ ~ <)) fc:tmur c):; ~ ocfi~.A ~) ~411, 2010 \"R fcl filfatsc. ~ ~ ~ ~ ~ f 3. 3:cfc1' Rlm<.1cff! 6i, \"~ ~ ~ <~ ~ <)) ~ ~ 3fcj,{\"aroT c}J ~ f.J:rs ~l\" ~riGl <)i\" m ~ ~ ~ afr ~ Uc@ ~ \"~ ~ ~ cn:rs ~> RlF.14.Ji, 2010\" ~TiG ~ ~I . 4. ~ Fclfilil.lill ~ rciWtc1iH 6 al, (\"ij;) ~ (6) <);° 3ra at f.lJ.o1fi:l~c1 ~ 3fn: m:~ ~ ~. 3f~ :- \"~ ~ ~ ~ ~ ~ rli1<.fif;cic1 ~ c); 3°tQ-zr ~ ~ <HiljRJrt QRlfDT 3q4lf.i'lr11 m ~- ~ mJ, ~, ~ 3flt~ 5Qch-{Oj ~ JJf\\}IJl4 Qfc-l,Hr.;:i ~ ~I\" \"(8) ~ ~ 3Q4~f•rlcil, 110 c):;. tit. JtR ~~~~cot~~ Q\"01l'(;fr ·<ITT~ 3,Qlc;cl mlil' ~ ~ c); ~ c); ~ ~ c); 30 ~ c); afuR ~ ~ sq4'1f.r1a1 3tR\" ~ cffi\" ~ q;tm\" I s. 3iRt Fc1Wtc11!11 A fc3WflliH 7 al lis (1) #, _ '3lT-RQr.=r ~ ~ ~, ~~ c);' ~ ~ FctWJ -·3c-41aq; cfitr.fl\" 3f~ ~ ~ cm Q,·.11~r1 <R ~~~,m~~~I 6. 3itt1 Pcim:«arl A ~ al, ,, ,, .. !, ' I I.I -- 2 of 10 -- : ; 1 !l 1 ~.; r· g:1 ,~ ~~ ~ ~ i ii - !i ~ I t if ~ f ~! i I re ~ ~ ,15~- i ~Mi i I ~t i ii 1~ 1 ~g! ~~ : I _ f t> i i_ ti t - ~ I I t ! i t i !! ; I I .t ~ r 1 ,~ \"' t g( ti; !I! ti £~: i ~ fa . ~t J JI ~i~ iii5 if J;~ M ,I& i O ~ ·( l 1v &. I is: - lg 'W\" jg '1& i ~ i ~ ! i ~ ~ ! ; i -~ ! t l ~ i ti : i ~ ~ ,. 7 l 1i ! t i I ~ 1 1 i ! ~ f ~ i : +I e i ! i ' I ! i* !i ,ti i Iii! i!t i:jtii !?: ~ ~ t m I l i I i i ~ i I ~ i 1 fl I); !~ 1 \"' ! -~ Ii :: f 1 j ~ ! ~ ~ . m j ~ w I - \"' ~ ~ i I. g J I - i ~ - -~ \" I i ts I 1 i ! : ~ ~ ~ ~ - ! i 4& I ,J ~ 1 t t ~ 5 i i ~ I ~ i 'Ii\\ !<w 'W, l~i~I i i~ ~,~ ~jfci~I~ cl,: -;; \"' i .fli '·.t .t f \"'~ ~ ~ ~ -ts ts~~ tt t r;im r; · ! i f ;L, ~I 1 !~ e i i!j ti; t~t:r,:rJ! ! ~ .t . ~! f ;i' ~ ~ ' !'.li ~ ~ii ef It Ii ti - ,. . ~ -- 3 of 10 -- 4 THE GAZETTE OF INDIA : EXTRAORDINARY [PART III-SEC. 4] (6) cffim 3ffi fc:lalali$c. 3TTUTfuf ~ 3rQlac6 ~ 3TTcffel \\.lfc'H~<ll ~ $ fffir 3wQ\" ~ ~ fi:l1r ~ ~ ~ ,~ rlf% ~ ~ftj\" $ 3rdT<=r ~ m3\" a-f.J@T ~ ~~) ~ 105 ~rc=r nc1i 4i'I 3r4IGoi !ITTfCTT CR\" f!\"a:ra:r ~ f (7) ~ ~ 3rQl&ai ~ ~ f.;lii~a 3fNR\" ~ tts ™ (tts° ts$~ M 1R fJ) $ 110 i;rfc:t~R, cftf> 3,QIC:\"1 m cfl'I\" 8:'f1RTT ~ I cs J ~ 3r-4Ic.c1 ~ ~ m:r cr ~ ~ * ~ am -w;>r.:it ~ ~ ~ \"H ~ $ ffiffi $ fi:l1r ~ wan ~ ~ ~ QR, ~ ~ t a.ft\" ~ t ffian ~ ~ ~ ~an ~ ~I 100 #.rrr me cmfr 3,Qic,ai ~ $ fc:ro\" Fclc'h ~ ~ (M) j11q_fchri t ~ ~ ~ $ ~ ~ ~ TR m- ~ ~ m~ ~ fa1J ~ 1 ~ ,a=rcrr ~ m ~3m c~> ffian cm- f1~cHfc:lc1 ~ ~ ~ cfcli\" ~ ~ cft'i\" ~ I ·, (9) SO .RJllcllc 3fR TIRt 3nVcJi im:@T ~ '5ti>tRI~ 3,Qic,\"1 ~ ~ ~ 3ft ~M ~ ff).-¢).,-i-t1 ~ a:TTs CR\" ~ ~ ~ ff~ ~ I ~ ~ f<n. oTfu.i:r 01.1.2014 ?.liT m ~ q~'if@' ~<fit~ nm so ~.ar. 3fR' nrn ~ tlE ~ cm;fr ~ fcrqcf 3,Qlc,i-l ~. ~ 3Rf:~ ~~ t ~ 3nq~~ ~ ~ ~ t; c'IT, ~ -H'l.-w1;;:i,H ~ms~ m- m cfi'r ~ t ~:«G--,ta ~ ~ 1 c10 ~ cfi'I qnm;jj.,:i1 ~ ~; til$UilcA1$\"1:t1.-f ~ <fr ~ 1 (12) ft~Jtj\", ~ 3tR \\.lklfinlll~fi<;f 3ITTT:t~3fl\" ~ ~ ~ ~~JIT cm-,~ m CR\" m ~ f.ig ~ ;i:I fc'lf.;lffi:1!4_,c ~ t ~. ~ 3ft ~. fm° ~ ~ ~ cm- ~ cft'i\" ~ I (13) ~ ~ 3r-Qlc,-, ~ <);- ~ CR\", m: ~ M cmfr ~ t;I\" ~ 1 ~-Rrt * ft:ro- ffiitj\" $ ~ ~~m qi)- ~ ~ * ft:l1r ~ ~ 3i=<llc..-i mr.:rr * qm- 1T<li m ~ ~ilfi~I ~~ ~~ fcrWJ ~CR\"~~~(~~ JtRftlwr ~$ ~ t ~ c1<hc114i'I ~) Rlfc-lllcA, 2010 * ~ ~ ~, ~ fc'IQ.ucJfi '$ ~r.:r $ ~ t ~ RR: ~~~I (14) 3c'Qlt.ci ~~TcIT t ~ f<1\"1w:m; t ~ ~. ~ ~ ~ :mai--m ~ ~ \"3(f ft~r;rr\" ~ -m ~ Rl~f'a!Sc ~ ~ ~ ~ I iii. 2 3fQldif ~. .ift ~ ~ ~cfi.(UI ftlti\\tiittct, 2007 (~ <}.- '(1,Q,;,jci ~ ~ (ict,;:fttBI 31'1ci'qi) $ ~ ~ cnJ oRror 'Em ftrs t ~ t fr <ticilf.;i(i ~I 200 AJ11c11c ~ 3lm\" ~ tts ~ cm;fr ~ 3,q1e;:o1 ~ ~ 100 ~ 3ITT\" ~ ~ ttg ~ clTTifr ~ ~ ~ ~. c1e11cfi<lu, 3tR ~4i'li:4i-lDI ~ ~ f.:!Mfc:IU!!a ~ ~~~ I -- 4 of 10 -- t • , [,w-r m-~4J 5 (1J ~ 3,q1acif ~ cfiT ~= ~ ~ ~ 1 100 ~ mc ~ ~ ~ m ~ ~ ~ c); \"fcfn: ~ ~ cn- rn-rn ~ ~ M ~ BTrhr ~ ~ ,fqtjlfi:lc1 ~ : MI (3) ~at 3r-Qle.cif ~ \"iji\" ~ \"{wrf ~ ;m ~ ~ ~ cm- ~ ~ ~ c); :ificR c):; ~ -a -mln ~ ~ Q'R1lfOT ~ ~ aT\"ff aft ~ cJitrt 1 ~ \"{!ffO'T ~ m ~m (~J W!ITT cm- fliHl~a ~ ~ ~ ~. ~ ~ ~ ~ I 3cfc'l fclf.::l.q<H at ~ of$. ~ {441,:ilo'l ~@ 3ITT\" ~ c):; ~-l c):; Jlffiftcfa ~ 3,Qle.o'l ~ clt1\" ~Mfi:1Rslc1 JNIITTJTT cfiT 3fojQlc>lcif clivlT mm- (1) V<fi 3,Qlc',cfi ~ ~ ~l{cfi~f.::lth ·rum cfiT 3fc=r:~ $.ftl?<(C: 3fffi $t1fct.?4fol ~ $~~lf;lcR, $.5flf.:'!14~Jl (~ t ~ t> ~ 519 at fclf;lgtQ: ~JIT -a~ ;itJ t'J'JTTI (2) 3,Qle.<A ~ 30:atcro-T ~ ~ 1l13l ~ 3,Qle.t1 $ 0.5% ~ ~ co)- ~ 'UTU cfiT 3@:~ .=,tr crtm, (3L,3,QIG,t1 ~ 3fTf ~ ~ 61000 ';A Fclf\"dlR.ll?. A3TT ~ ~ ~ ~ tm1 'ij~@fc.li ~ ~ ~ 1 .filh.r, 2014 ~ gamft ~I (4) (;l<cA'lf.;'lcfi <Re, ~ rum 3@:e:fQ'OT 3fi°{ ~ cfiT ~ ~ Q'lffi' ~ ~ if rftt at cii\"a:r ~ ~ Vco ~ ~ ~ Jffi ~ ~ ~ orfror ~Q~ CJwR ~ 3f;c>1~a ~I ~ ~ fcp ~ ~ c):; ~ffift.i:frl, zja' ~ ~ ~ QRlifOT ~ 'tfT 3r41e.cif ~. ~ aft~. (,i<<Mlf.:'!lcfi tfitc 'll'T ~ mu 3t=r:~ m 'fFT q;r a:rrq;rr ~ ~. ~ ~ ~ i:Ja cm- ~ f(tTo,f ~ ~ s thltiRcFH'i c):; ~ ~ ~ ~I nr. 2. ~ fti~:cut1 ~ m'1t ~~18tcrrfr'w~ 6 Jrm\"~~c81'tllfrwcffi'Mt(cn' 3\"fl'$tmmr~ ~ 5c'Qi~ri ~ $ ~ (1) 3,Qle.4i R~~ ~ft;J qft;c.fr~.,;'J~ yffifw41~1n>J ~ ID,~ cfrl' ~ ~ at ffm:f ~ -~ fcp 0.95 ffi'.rr ~ 0.95 ~ cfrl' lft;m3rr c):; afuR ~ thRcfi cm- i1o,RT ~al~ I (2) ~ 5,Qlc,o-i ~ 47.s ~ ~ 52 ~ cfi'I\" ~cf~-fll f-,r M ~ m M ~m, Wft ~ . 49.S ~ ~ 50.5 ~ ~ ,tm~·.fil t5r at ~ 5,Qle.<A cf;l\" 3TTqj'a ~ $ .:rrnr. ~ I ~ ~ fcp 3c@ f.::11\\Qlc,cif ~ ~ ~ ~ m)' -~ 3rt'{ ± 5 1Jfc:lv@ n<Jl $ ~ ~ c); ~~~ t;rlG, ~ ~ 1 (3) 66 -m;cft 3ITT' nr ~ 3itR c):; ~ 'ft'!'\"{ tR ~ ~ s,41c,o1 rt~r.=r fts' ~ ~ iTa ~ ~ ~=-~ ~ i:n: ~ ,:rq; m ~aft ~ tn: ;mtr ~ oo ~ @tr c'lcn f;!IMfi:IR;la cm, JITToR ~ f?;q th\"{ ;;mfr ~I lr 4 t '1 e-.;11 IB -:h -- 5 of 10 -- 6 THE GAZETTE OF INDIA : EXTRAORDINARY 0.85_ ------------------- -- -------------------- O. i ~----r 0 300 I • I I 3000 [PART III-SEC. 4] ~ ~ ftti' ~ ~ $ ~ ~ 3rQlc,iii ffifiii' \"at ~ ~ 3rQlc,c1 ~ ~ ~ $ -HiHl14il1 al ~ fctqn cj)f 3c-Ql?;.,.f ~ I ~ ~ 3ITT' ftti' ~ f?;tJ c);' at-0.1, ~ .5rQ!c,c1 mr.:r ~ ~ ~ ~ 3m@t ~ ol\"il\" ~ ~ ~ ~ ~ JiITT=f ~ ~ m 300 \"11M1flciis r);\" ~. ~ 3fr cfi1I' ~ ~ 1 (2) 66 ~ 3ltt 3\"lf \"t 3\"CR' $ ~ @'\"{ Q\"{ ~ ~ 3rQic,q'i 'R'Qlcf <ITT \"Qcfl ~ ~ $ ~ ;i:r ~ ~ Jrrr:lffQ\"OT c~r.:r) <ITT f..lai~a ~ cf.)' ~ ~ ~ ~ :RR ~ ~ $ ~rr <li 3fT1IT{ Q\"{ ffi~ fcITTr ~ af ~a=ra, ~ I ~ ~ fcJl ~ n\"1 ~a:rcr ~~~al <ITT\"$'~~~ qi\"{ \"{t)' 3,q1ac1 ~ c), m:: fcnv ~ 3ITT' 3.,.f\" cfi'I' aTcJfffi io ~ ~ <R ~ tl\"rt'f fmjn 3c-Qie,rit ~ 6Rf ~1aftc;1f1 ~ ~ ~~$~~~~I cs) ~ s,q1ao1 ffiro:rr c), ~ ~ nciil41g m- ~ al ~ ~ ~ c), iRr.rr 3 io ~ ~ ~Qr.TI'$~ ~- fcH~~ISe. ~ $ ~ <# ~ ~I «. 3. $.f ~A~iftf ~ m ;t1- ~fif ~ nit« ~ 6 1fm W ~ ~ nlfRi q:rr ~ ~ ~ ~ 3r-<11a\"\" ~ ~ n:ttr 1 fm:Jn 3i-Qlc,,ii qi\"Q.fl' 3f\\\"{ 3lf ~ w,m;fr $ ~ ~ fcrqa 3,Qle.c1 ~ {14!fsir1 ~ tm=tR ~ <1itJt 3ITT' 3cl 3\"QTlrr Q\"{ ~ ffe ~ fcn <1cfii.1.,1$J c-4c.l(;i~c11 $ 3f~ (~.1) 3fr{ (R2) ;il Fclf.?tglic. ~<ITT~~<);\" R1ll fcnv ~I\"; {\"«). ~ $ iRr.rr IV<);\"~ 6 $ ~ Q\"{ Wlc1-c1~R!lct ~ ~ ~. 3f~:- 6. ~-~ ~~4m<fal 3l'R~<lT~3l«rffl~ ~'i:11Pla ~~<lT~~~.'lil'3TI!'-~ffl~ ID\"(T ~ a:fqcff ffi\"ZOT ~ ~ 3,~frl c\\ ~ ~ ~ cf<fi~ 9lffl <i°f ~I 31-j#l.~mft ~ \"ffiq' ~ m ~ ~ ~ ~ ~ .f .f?r llt ~ I ~-~-!ft.~ ~-lll/4/3'!ID~/ 150113J ~-·ft,;qvr :~~mm~~ ~ ft. 12/1:!;'ffiiQ,tic:.1i1M 3f\"lv.r1 Q,1~~. \"ITT& 21 ~. 2007 m-u ~ ~ ~ ~ I ' ,, ' -- 6 of 10 -- ,I [iwr III-~ 4] MINISTRY OF POWER (Central Electricity Authority) NOTIFICATION 7 New Delhi, the 15th October, 2013 No.12/X/STD(CONN)/GM/CEA.-Whereas the draft of the Central Electricity Authority (Technical Standard for Connectivity to the Grid) (Amendment) Regulations, 2012 were published, under sub-section (3) of section , 177 of the Electricity Act, 2003 (36 of 2003) and rule 3 of the Electricity (Procedure for previous Publication) Rules, 2005 on 16th March, 2012; Now, therefore, in exercise of powers conferred by section 7 and clause (b) of section 73 read with sub-section (2) of section 177 of the Electricity Act, 2003, the Central-Electricity Authority hereby makes the following regulations to amend the Central Electricity Authority (Technical Standards for Connectivity to the Grid) Regulations, 2007, namely:-- 1. Short title and commencement. - (l)These regulations may be called the Central Electricity Authority (Tec.hnical Standards for Connectivity to the Grid) Amendment Regulations, 2013. (2) These Regulations shall come into force on the date of their publication in the Official Gazette. 2. In the Central Electricity Authority (Technical Standards for Connectivity to the Grid) Regulations, 2007 1 (hereinafter referred to as the said regulations), in regulation 2, - (a) for clause (10) the following clause shall be substituted, namely:- \"Earthing\" means electrical connection between non-energized conducting parts and the general mass of earth by an earthing device\"; (b) in clause (14) the following parag~aph shall be added at the end, namely:- \"In case of Solar Photo voltaic generating station, each inverter along with associated modules will be reckoned as a separate generating unit\"; (c) for clause (17) the following clause shall be substituted, namely:- \"Interconnection point\" means a point on the grid, including a sub-station or a switchyard, where the interconnection is established between the facility of the requester and the grid and where electricity injected into -or drawn from the grid can be measured unambiguously for the requester\"; · (d) after clause (17), the following clause shall be inserted, namely:- ·'( r! A) \"Inverter\" means a device that changes direct current power into alternating current power\"; (e) for clause (19) the following clause shall be substituted, namely:- \"Maximum Continuous Rating\" (MCR) will carry same mearung as defined in the Central Electricity Authority (Technical Standards for Construction ofElectrical Plants and Electric Lines) Regulations, 201 O\"; (f) clause 20 shall be omitted; (g) after clause (28) the following dause shall be inserted, namely:- \"(28A) \"Standard Protection\" means electrical protection functions specified in Central Electricity Authority (Technical Standards for Construction ofElectrical Plants and Electric Lines) Regulations, 2010\". $ 3. in the said regulations, for the words ·\"Central Electricity Authority ( Grid Standards for Operation and Maintenance of Transmission Lines) as and when they come into force\" the words \"Central Electricity Authority (Grid Standards) Regulations, 2010\", shall be substituted. · 4. In regulation 6 of the said regulations, - (a) in clause (6) the following proviso shall be Inserted at the end, namely:- \" Provided that in order to carry out the said study, the requester shaH present the mathematical model of the equipment in accordance with the requirements as stipulated by the Appropriate Transmission Utility or distribution licensee, as the case may be.\" (b) after clause (7) following clause shall be inserted, namely:- \"(8) The State Transmission Utility shall inform the Central Transmission Utility and the Authority, within thirty days of acceptance of application for connectivity of a generating station to electricity system operating at 110 kV and above.\" 5. In regulation 7 of the said regulations, in clause (1) for the words \"owner of the sub-station where\" the words\" generating company or licensee operating the electricity system to which\" shall be substituted. 6. In the Schedule of the said regulations, - (a) for Part 11 the following shall be substituted, namely:- -- 7 of 10 -- 8 THE GAZETTE OF INDIA : EXTRAORDINARY [PART III-SEC. 4] \"Part H Connectivity Standard applicable to the generating stations A. Connectivity Standards applicable to the Generating Stations other than wind and generating stations using inverters These generating stations shall comply with the following requirements besides the general connectivity conditions given in the said regulations and Part I of the schedule:- Al. For Generating stations which are connected on or after the date on which Central Electricity Authority (Technical Standards for Connectivity of the Grid) Regulation, 2007 became effective ( 1) The excitation system for every generating unit:-- (a) Sh4Ph,ave.state of the art excitation system; (b}Shall; have Automatic Voltage Regulator (AVR). Generators of 100 MW rating and above shall have Automatic Voltage Regulator with digital control and two separate channels having independent inputs and automatic changeover; and (c) The Automatic Voltage Regulator of generator of 100 MW and above shall include Power System Stabilizer (PSS). (2) The Short-Circuit Ratio (SCR) for generators shall be as per IEC-34. (3) The generator transformer windings shall have delta connection on low voltage side and star connection on high voltage side. Star point of high voltage side shall be effectively (solidly) earthed so as to achieve the Earth Fault Factor of 1.4 or less. (4) All generating machines irrespective of capacity shall have electronically controlled governing system with appropriate speed/load characteristics to regulate frequency. The governors of thermal generating units shall have a droop of 3 to 6% and those of hydro generating units Oto l 0%. (5) Generating Units located near load centre, shall be capable of operating at rated output for power factor varying between 0.85 lagging (over-excited) to 0.95 leading (under-excited) and Generating Units located far from load centres shall be capable of operating at rated output for power factor varying between 0.9 lagging ( over-excited) to 0.95 leading (under-excited). Provided that all generating units commissioned on or after O1.01.2014, shall be capable of operating at rated ou~ut fo~_p'ower factor varying between 0.85 lagging (over-excited) to 0.95 leading (under-excited). Provided further that the above performance shall also be achieved with voltage variation of± 5% of nominal, frequency variation of+ 3% and -5% and combined voltage and frequency variation of ±5%. However, for gas turbines, the above performance shall be achieved for voltage variation of ±5%. (6) The coal and lignite based thermal generating units shall be capable of generating up to 105% of Maximum Continuous Rating (subject to maximum load capability under Valve Wide Open Condition) for short duration to prqvide the frequency response. (7) The hydro generating units shall be capable of generating up to 110% of rated capacity (subject to rated head being available) on continuous basis. (8) Every generating unit shall have standard protections to protect the units not only from faults within the units and within the station, but also from faults in transmission lines. For generating units having rated capacity greater than I 00 MW, two independent sets of protections acting on two independent sets of trip coils fed from independent Direct Current (DC) supplies sh~ll be provided. The protections shall include but not be limited to the Local Breaker Back-up (LBB)'protection. (9) Hydro generating units having rated capacity of 50 MW and above shall be capable of operation in synchronous condenser mode, wherever feasible. Provided that hydro generating units commissioned on or after 01.01.2014 and having rated capacity of 50 MW and above shall be equipped with facility to operate in synchronous condenser mode, if necessity for the same is established by the: interconnection studies. (I 0) Bus bar protection shall be provided at the switchyard of all generating station. ( 11) Automatic synchronisation facilities shall be provided in the requester's Project. ( 12) The station auxiliary power requirement, including voltage and reactive requirements, shall not impose operating rest~ictions on the grid beyond those specified in the Grid Code or state Grid Code as the case may be. ( 13) In case of hydro generating units, self-starting facility may be provided. The hydro generating station may also have a small diesel generator for meeting the station auxiliary requirements for black start. Provided that hydro generating units shall have black start facilities in accordance with provisions of Central Electricity Authority (Technical Standards for Construction of Electrical Plants and Electric Lines) Regulations, 2010 from the date of publication of these Regulations. (14) The standards in respect of the switchyard associated with the generating stations shall be in accordance with the provisions specified in respect of 'Sub-stations' under Part III of these Standards. -- 8 of 10 -- [ 'qpT III - \"@U\":S 4 ] 9 A2. Generating stations which were already connected to the grid on the date on which Central Electricity Authority (Technical Standards for Connectivity to the Grid) Regulations, 2007 became effective For thermal generating units having rated capacity of 200 MW and above and hydro units having rated capacity of 100 MW and above, the following facilities would be provided at the time of renovation and modernization. ( 1) Every generating unit shall have Automatic Voltage Regulator. Generators having rated capacity of l 00 MW and above shall have Automatic Voltage Regulator with two separate channels having independent inputs and automatic changeover. (2) Every generating unit of capacity having rated capacity higher than l 00MW shall have Power System Stabilizer. (3) All generating units shall have standard protections to protect the units ,not only from faults within the units and within the station but also from faults in transmission lines. The protections shall include but not limited to the Local Breaker Back-up (LBB) protection. B. Connectivity Standards applicable to the Wind generating stations and generating stations using inverters These generating stations shall comply with the following requirements besides the general connectivity conditions given in the said regulations and Part I of the Schedule:- Bl. Requirements with respect to Harmonics, Direct Current (DC) Injection and Flicker ( l) Harmonic current injections from a generating station shall not exceed the limits specified in Institute of Electrical and Electronics Engineers (IEEE) Standard 519. 1(2) The Generating station shall not inject DC current greater than 0.5 % of the full rated output at the interconnection point. (3) The generating station shall not introduce flicker beyond the limits specified in IEC 61000. Provided that the standards for flicker will come into effect from 1st April 2014. (4) Measurement of harmonic content, DC injection and flicker shall be done at least once in a year in presence of the parties concerned and the indicative date for the same shall be mentioned in the connection agreement; Provided that in addition to annual measurement, if distribution licensee or transmission licensee or the generating company, as the case may be, desires to measure harmonic content or DC-injection or flicker, it shall inform the other party in writing and the measurement shall be carried out within 5 working days\"; 82. For generating station getting connected on or after completion of 6 months from date of publication of these Regulations in the Official Gazette. (1) The generating station shall be capable of supplying dynamically varying reactive power support so as to m~ntain power factor within the limits of 0.95 lagging to 0.95 leading. (2) The generating units shall be capable of operating in the frequency range of 47.5 Hz to 52 Hz and shall be able to deliver rated output in the frequency range of 49.5 Hz to 50.5 Hz. Provided that above performance shall be achieved with voltage variation of up to ± 5% subject to availability of commensurate wind speed in case of wind generating stations and solar insolation in case of solar generating stations. (3) Wind generating stations connected at voltage level of 66 kV and above shall remain connected to the grid when voltage at the interconnection·point on any or all phases dips up to the levels depicted by the thick lines in the following curve: 0.85_ 0.1 0 300 3000 Time (mS) Where Vr!Vn is the ratio of the actual voltage to the nominal system voltage at the interconnection point -- 9 of 10 -- 10 THE GAZETTE OF INDIA : EXTRAORDINARY [PART III-SEC. 4] Provided that during the voltage dip, the individual wind generating units in the generating station shall generate active power in proportion to the retained voltage; Provided further that during the voltage dip, the generating station shall maximise supply of reactive current till the time voltage starts recovering or for 300 ms, which ever time is lower. (4) Wind generating station connected at voltage level of 66 kV and above shall have facility to control active power injection in accordance with a set point, which shall be capable of being revised based on the directions of the appropriate Load Despatch Centre. Provided that as far as possible, reduction in active power shall be done without shutting down an operational generating unit and with reduction being shared by all the operational generating units pro-rata to their capacity. (5) The standards in respect of the switchyard associated with the generating stations shall be in accordance with the provisions specified in respect of 'Sub-stations' under Part III of these Standards. B3. For generating units which are connected before and upto 6 months after the date of publication of these Regulations in the Official Gazette The generating company and the licensee of the electricity system to which the generating station is connected shall mutually discuss and agree on the measures which can be taken to meet the standards specified in (B 1) and (B2) subject to technical feasibility\"; (b) in Part IV for clause 6, the following clause shall be substituted, namely:- \"6. Back-energization / The bulk consumer shall not energize transmission or distribution system by injecting supply from his generators or any other source either by automatic controls or manually unless specifically provided for in the connection agreement with the Transmission or Distribution Licensee\". M. S. PURI, Secy. [ADVT. IW4/E:xiy./150/13] Foot note: The principal regulations were published in the Gazette oflndia vide number 12/X/STD(CONN)/GM/CEA dated the 21st February 2007. Printed by the Manager, Government of India Press, Ring Road, Mayapuri, New Delhi-110064 and Published the Controller of Publications, Delhi-110054. -- 10 of 10 --",
  "fetched_at": "2026-04-13T19:30:02.731Z"
}
