{
  "act_id": "the_manipur_panchayati_raj_act_1994__1899",
  "section_number": "80",
  "section_id": "42770",
  "title": "Section 80",
  "content": "(1) A Zilla Parishad may subject to the provisions of this Act and the rules made thereunder and with the previous sanction of the Government, by notification, make regulations to carry out the purposes of this Act in so far as it relates to its powers and duties. (2) The regulations made under sub-section (1) shall be subject to the condition of previous publication and such publication shall be in such manner as may be prescribed.",
  "footnote": "",
  "metadata": {
    "source": "IndiaCode",
    "act_url": "https://www.indiacode.nic.in/handle/123456789/1899?view_type=browse",
    "fetched_at": "2026-03-02T11:30:34.947Z"
  }
}