{
  "act_id": "the_companies_profits_surtax_act_1964__1370",
  "section_number": "6",
  "section_id": "33069",
  "title": "Section 6",
  "content": "(1) For the purposes of making an assessment under this Act, the 1[Assessing Officer] may serve on any, person who has furnished a return under sub-section (1) of section 5 or upon whom a notice has been served under sub-section (2) of section 5 (whether a return has been furnished or not) a notice requiring him on a date therein to be specified, to produce or cause to be produced such accounts or documents or evidence as the 2[Assessing Officer] may require for the purposes of this Act and may from time to time serve further notices requiring the production of such further accounts or documents or other evidence as he may require. (2) The 2[Assessing Officer], after considering such accounts, documents or evidence, if any, as he has obtained under sub-section (1) and after taking into account any relevant material which he has gathered, shall, by an order in writing, assess the chargeable profits and the amount of the surtax payable on the basis of such assessment.",
  "footnote": "1. Subs. by Act 4 of 1988, s. 187, for \"Income-tax Officer\" (w.e.f.1-4-1988). 2. Subs. by Act 4 of 1988, s.187, for \"Income-tax Officer\" (w.e.f.1-4-1988).",
  "metadata": {
    "source": "IndiaCode",
    "act_url": "https://www.indiacode.nic.in/handle/123456789/1370?view_type=browse",
    "fetched_at": "2026-03-02T10:40:26.026Z"
  }
}