{
  "act_id": "the_national_commission_for_minority_educational_institutes_act_2004__1897",
  "section_number": "12",
  "section_id": "23487",
  "title": "Section 12",
  "content": "(1) If any dispute arises between a minority educational institution and a 1 *** University relating to its affiliation to such University, the decision of the Commission thereon shall be final. (2) The Commission shall, for the purposes of discharging its functions under this Act, have all the powers of a civil court trying a suit and in particular, in respect of the following matters, namely:-- (a) summoning and enforcing the attendance of any person from any part of India and examining him on oath; (b) requiring the discovery and production of any document; (c) receiving evidence on affidavits; (d) subject to the provisions of sections 123 and 124 of the Indian Evidence Act, 1872 (1 of 1872), requisitioning any public record or document or copy of such record or document from any office; (e) issuing commissions for the examination of witnesses or documents; and (f) any other matter which may be prescribed. 2 [(3) Every proceeding before the Commission shall be deemed to be a judicial proceeding within the meaning of sections 193 and 228, and for the purposes of section 196, of the Indian Penal Code (45 of 1860) and the Commission shall be deemed to be a civil court for the purposes of section 195 and Chapter XXVI of the Code of Criminal Procedure, 1973 (2 of 1974).]",
  "footnote": "1. The word \"Scheduled\" omitted by s. 5, ibid. (w.e.f. 23-1-2006). 2. Ins. by Act 18 of 2006, s. 5 (w.e.f. 23-1-2006).",
  "metadata": {
    "source": "IndiaCode",
    "act_url": "https://www.indiacode.nic.in/handle/123456789/1897?view_type=browse",
    "fetched_at": "2026-03-02T14:37:16.455Z"
  }
}