{
  "act_id": "the_international_financial_services_centres_authority_act_2019__14009",
  "section_number": "4",
  "section_id": "49895",
  "title": "Section 4",
  "content": "(1) The Central Government shall, by notification, for the purposes of this Act, establish an Authority by the name of the International Financial Services Centres Authority. (2) TheAuthority shall be a body corporate having perpetualsuccession and a common seal, and subject to the provisions of this Act, with power to enter into and execute contracts, acquire, hold and dispose of property, both movable and immovable, and shall, by the said name, sue and be sued. (3) The head office of the Authority shall be at such place as the Central Government may, by notification,decide. (4) The Authority may, with the prior approval of the Central Government, establish its offices at other places in India or outside India.",
  "footnote": "",
  "metadata": {
    "source": "IndiaCode",
    "act_url": "https://www.indiacode.nic.in/handle/123456789/14009?view_type=browse",
    "fetched_at": "2026-03-02T15:14:36.861Z"
  }
}