{
  "act_id": "the_airports_authority_of_india_act_1994__1979",
  "section_number": "28N",
  "section_id": "16594",
  "title": "Section 28N",
  "content": "1[28N. Offences under this Chapter.--(1) Whoever, unlawfully occupies any airport premises, shall be punishable with imprisonment for a term which may extend to six years and with fine. (2) Whoever fails to comply with any order of the eviction officer or the 2[High Court] under this Chapter shall be punishable with imprisonment for a term which may extend to seven years and with fine. (3) If any person who has been evicted from any airport premises under this Chapter again occupies the premises without authority for such occupation, he shall be punishable with imprisonment for a term which may extend to ten years and with fine. (4) The court may, while convicting a person under sub-section (3), make an order for evicting that person summarily and he shall be liable to such eviction without prejudice to any other action that may be taken under this Chapter.]",
  "footnote": "1. Ins. by Act of 43 of 2003, s. 8 (w.e.f. 1-7-2004). 2. Subs. by Act 33 of 2021, s. 19, for “Tribunal” (w.e.f. 4-4-2021).",
  "metadata": {
    "source": "IndiaCode",
    "act_url": "https://www.indiacode.nic.in/handle/123456789/1979?view_type=browse",
    "fetched_at": "2026-03-02T11:31:44.173Z"
  }
}