{
  "sub_id": "notifications_23-01-2008_notification_dated_23_jan_2008_d40f5447b4e8_",
  "parent_act_id": "the_commissions_for_protection_of_child_rights_act_2005__2056",
  "title": "Notification dated 23 Jan 2008",
  "type": "notification",
  "category_label": "Notifications",
  "source": "IndiaCode",
  "source_url": "https://www.indiacode.nic.in/ViewFileUploaded?path=AC_CEN_9_17_00001_200604_1517807317700/notificationindividualfile/&file=E_102_2010_008+23-Jan-2008.pdf",
  "detection_method": "modal-table-scan",
  "document_date": "23-01-2008",
  "description": "Notification dated 23 Jan 2008",
  "hindi_description": null,
  "file_title": "E_102_2010_008 23-Jan-2008.pdf",
  "duplicate_count": 0,
  "alternate_source_urls": [],
  "alternate_file_titles": [],
  "alternate_descriptions": [],
  "document_format": "pdf",
  "extraction": {
    "content_type": "application/pdf",
    "final_url": "https://upload.indiacode.nic.in/showfile?actid=AC_CEN_9_17_00001_200604_1517807317700&type=notification&filename=E_102_2010_008%2023-Jan-2008.pdf",
    "num_pages": 1,
    "parser": "pdf-parse",
    "status": "parsed",
    "error_message": null,
    "error_code": null,
    "error_status": null
  },
  "text": "If\"Alt *Alb TOb-33004/99 4*- 4\"Tr a 41v1 .$1 The Gcmette of 'Indiaauirami EXTRAORDINARY will—Tan 3-3Q- 'U PART II—Section 3—Sub-section (ii) 'SIAM! 14<tAr( PUBLISHED BY AUTHORITY 102) '4 F erfl, apiti4 clemt Aici 24, 2008/Allif 4, 1929 No. 102] NEW DELHI, THURSDAY, JANUARY 24, 2008/MAGHA 4,1929 REGD. NO. D. L.-33004,99 TrfOrr Rat AM firwrfr aftprit 'qf fkml, 23 41.14, 2008 • W1.311% 138(31).—etitich 3:iftslqo VIATuT 3ThiTITT airlift :Fr, 2005 (2006 4) *t *MT 3(2 ) (V1) aigRuT lEhl *Kew AM alvTAT to-114 Try- * OR 4 fitiin 71)Tt lurr, 4-47-19000l qizich *Err alrth* (-14t4 t WI 4 wrk* dal' 4 RIM *Kew # flfiti1 fit It Livti4 41 clich 6 ffrdag, 2007 atenralr-cf. 7b-T.311. 1497(30 fir ctrtril * I (T5T. 74. 3-5/2006 ItsGri] W4A)19. qq4, 0:14 MINISTRY OF WOMEN AND CHILDDE'VELOPMENT NOTIFICATION New Delhi, the 23rd January, 2008 S.O. 138(E).—In pursuance of Section 3(2)(b) of the Commissions for Protection of Child Rights Act, 2005 (4 of 2006) the Central Government hereby rescinds the notification of Government of India in the Ministry of Women and Child Development No. S.O. 1497(E) dated 6th September, 2007 regarding nomination of Ms. Nighat Shafi, 16, A, Gogji Bagh, Srinagar-190001 as a Member of the National Commission for Protection of Child Rights in the field of child psychology or sociology. [7. No. 3-5t2006 CW] LOVELEEN KACKER, it. Secy. 251 GI/2008 Printed by the Manager, Govt. of India Press, Ring Road, Mayapuri, New Delhi-110064 and Published by the Controller of Publications, Delhi-110054. -- 1 of 1 --",
  "fetched_at": "2026-04-11T11:45:53.221Z"
}
